rubin_jupyter_utils/lab/__init__.py
rubin_jupyter_utils/lab/_version.py
rubin_jupyter_utils/lab/notebook/__init__.py
rubin_jupyter_utils/lab/notebook/catalog.py
rubin_jupyter_utils/lab/notebook/forwarder.py
rubin_jupyter_utils/lab/notebook/utils.py
rubin_jupyter_utils/lab/rubinlabapp/__init__.py
rubin_jupyter_utils/lab/rubinlabapp/labhubapp.py
rubin_jupyter_utils/lab/rubinlabapp/rubinlabapp.py
rubin_jupyter_utils/lab/serverextensions/__init__.py
rubin_jupyter_utils/lab/serverextensions/display_version/__init__.py
rubin_jupyter_utils/lab/serverextensions/display_version/handlers.py
rubin_jupyter_utils/lab/serverextensions/hub_comm/__init__.py
rubin_jupyter_utils/lab/serverextensions/hub_comm/handlers.py
rubin_jupyter_utils/lab/serverextensions/query/__init__.py
rubin_jupyter_utils/lab/serverextensions/query/handlers.py
rubin_jupyter_utils/lab/serverextensions/query/templatemap.py
rubin_jupyter_utils/lab/serverextensions/settings/__init__.py
rubin_jupyter_utils/lab/serverextensions/settings/handlers.py
rubin_jupyter_utils.lab-0.13.0.dist-info/LICENSE
rubin_jupyter_utils.lab-0.13.0.dist-info/METADATA
rubin_jupyter_utils.lab-0.13.0.dist-info/WHEEL
rubin_jupyter_utils.lab-0.13.0.dist-info/entry_points.txt
rubin_jupyter_utils.lab-0.13.0.dist-info/top_level.txt
rubin_jupyter_utils.lab-0.13.0.dist-info/RECORD
